{
  "gameweek": 28,
  "generatedAt": "2026-03-03T13:11:40.755Z",
  "predictions": [
    {
      "homeTeam": "Liverpool FC",
      "awayTeam": "Chelsea FC",
      "predictedScore": {
        "home": 1,
        "away": 1
      },
      "winner": "draw",
      "confidence": 60,
      "analysis": "Both sides have shown defensive solidity this season, but Liverpool's attacking threat could be too much for Chelsea. Expect a tightly contested match.",
      "probabilities": {
        "homeWinPct": 25,
        "drawPct": 30,
        "awayWinPct": 45,
        "bttsYesPct": 80,
        "over25Pct": 60
      },
      "form & history": {
        "formHome": "LWWWW",
        "formAway": "WWWDW",
        "h2hSummary": "Home 3W-2D-1L in last 5 meetings",
        "homeLeaguePosition": 5,
        "awayLeaguePosition": 7
      },
      "team stats": {
        "homeGoalsPerGame": 1.8,
        "awayGoalsPerGame": 1.2,
        "homeConcededPerGame": 1.2,
        "awayConcededPerGame": 1.5,
        "homeXGPerGame": 1.5,
        "awayXGPerGame": 1.2,
        "homePossessionPct": 53,
        "awayPossessionPct": 47,
        "homeShotsPerGame": 12.5,
        "awayShotsPerGame": 9.8,
        "homeCleanSheetPct": 40,
        "awayCleanSheetPct": 50
      },
      "players": {
        "keyPlayerHome": "Mohamed Salah — 10 goals, pace and skill",
        "keyPlayerAway": "Kai Havertz — 5 goals, creativity and vision",
        "injuriesHome": [
          "Joe Gomez (ankle)"
        ],
        "injuriesAway": [
          "N'Golo Kanté (hamstring)"
        ]
      },
      "tactical analysis": {
        "homeFormation": "4-3-3",
        "awayFormation": "4-2-3-1",
        "tacticalMatchup": "Liverpool's high press will test Chelsea's defense, while Chelsea's midfield control could limit Liverpool's attacking opportunities.",
        "keyBattles": [
          "Mohamed Salah vs Reece James"
        ],
        "strengthsHome": [
          "Pace and skill on the wings",
          "Clinical finishing"
        ],
        "strengthsAway": [
          "Midfield control",
          "Defensive solidity"
        ],
        "weaknessesHome": [
          "Vulnerability on the counter"
        ],
        "weaknessesAway": [
          "Lack of pace in midfield"
        ]
      },
      "scoreline probabilities": [
        {
          "score": "1-1",
          "pct": 25
        },
        {
          "score": "2-1",
          "pct": 18
        },
        {
          "score": "0-0",
          "pct": 15
        }
      ],
      "match flow": {
        "halfTimePrediction": "0-0",
        "firstGoalTeam": "either",
        "matchTempoRating": 7,
        "dangerRating": 3
      },
      "additional markets": {
        "over15Pct": 90,
        "over35Pct": 30,
        "homeCleanSheetChance": 20,
        "awayCleanSheetChance": 40,
        "totalCornersEstimate": 9.5,
        "totalCardsEstimate": 3
      },
      "reasoning": [
        "Liverpool's home form has been solid this season.",
        "Chelsea's away form has been inconsistent.",
        "The head-to-head record favors Liverpool.",
        "Both teams have shown defensive solidity this season."
      ],
      "verdict": "A tightly contested draw is likely at Anfield.",
      "matchDate": "2026-03-07T15:00:00Z"
    },
    {
      "homeTeam": "Manchester City FC",
      "awayTeam": "West Ham United FC",
      "predictedScore": {
        "home": 3,
        "away": 0
      },
      "winner": "home",
      "confidence": 80,
      "analysis": "Manchester City's attacking prowess and home form make them strong favorites to win this match. West Ham's defense has struggled this season.",
      "probabilities": {
        "homeWinPct": 80,
        "drawPct": 10,
        "awayWinPct": 10,
        "bttsYesPct": 70,
        "over25Pct": 90
      },
      "form & history": {
        "formHome": "WWWWD",
        "formAway": "DWLWW",
        "h2hSummary": "Home 5W-2D-1L in last 5 meetings",
        "homeLeaguePosition": 1,
        "awayLeaguePosition": 15
      },
      "team stats": {
        "homeGoalsPerGame": 3.2,
        "awayGoalsPerGame": 1.8,
        "homeConcededPerGame": 1,
        "awayConcededPerGame": 2.2,
        "homeXGPerGame": 2.5,
        "awayXGPerGame": 1.5,
        "homePossessionPct": 60,
        "awayPossessionPct": 40,
        "homeShotsPerGame": 14.5,
        "awayShotsPerGame": 10.2,
        "homeCleanSheetPct": 70,
        "awayCleanSheetPct": 30
      },
      "players": {
        "keyPlayerHome": "Erling Haaland — 20 goals, clinical finishing",
        "keyPlayerAway": "Jarrod Bowen — 5 goals, pace and skill",
        "injuriesHome": [],
        "injuriesAway": [
          "Vladimir Coufal (ankle)"
        ]
      },
      "tactical analysis": {
        "homeFormation": "4-3-3",
        "awayFormation": "4-2-3-1",
        "tacticalMatchup": "Manchester City's high press will test West Ham's defense, while West Ham's midfield control could limit Manchester City's attacking opportunities.",
        "keyBattles": [
          "Erling Haaland vs Declan Rice"
        ],
        "strengthsHome": [
          "Attacking prowess",
          "Midfield control"
        ],
        "strengthsAway": [
          "Defensive solidity"
        ],
        "weaknessesHome": [
          "Vulnerability on the counter"
        ],
        "weaknessesAway": [
          "Lack of pace in midfield"
        ]
      },
      "scoreline probabilities": [
        {
          "score": "3-0",
          "pct": 30
        },
        {
          "score": "2-0",
          "pct": 20
        },
        {
          "score": "1-0",
          "pct": 15
        }
      ],
      "match flow": {
        "halfTimePrediction": "2-0",
        "firstGoalTeam": "home",
        "matchTempoRating": 8,
        "dangerRating": 4
      },
      "additional markets": {
        "over15Pct": 95,
        "over35Pct": 40,
        "homeCleanSheetChance": 80,
        "awayCleanSheetChance": 10,
        "totalCornersEstimate": 10.5,
        "totalCardsEstimate": 3.5
      },
      "reasoning": [
        "Manchester City's home form has been excellent this season.",
        "West Ham's away form has been poor.",
        "Manchester City's attacking prowess makes them strong favorites to win.",
        "West Ham's defense has struggled this season."
      ],
      "verdict": "Manchester City are likely to win comfortably at home.",
      "matchDate": "2026-03-07T15:00:00Z"
    },
    {
      "homeTeam": "Tottenham Hotspur FC",
      "awayTeam": "Nottingham Forest FC",
      "predictedScore": {
        "home": 2,
        "away": 0
      },
      "winner": "home",
      "confidence": 70,
      "analysis": "Tottenham's home form has been solid this season, and they should be able to beat a struggling Nottingham Forest side.",
      "probabilities": {
        "homeWinPct": 70,
        "drawPct": 15,
        "awayWinPct": 15,
        "bttsYesPct": 50,
        "over25Pct": 60
      },
      "form & history": {
        "formHome": "WWWWW",
        "formAway": "LWWWL",
        "h2hSummary": "Home 4W-1D-1L in last 5 meetings",
        "homeLeaguePosition": 6,
        "awayLeaguePosition": 18
      },
      "team stats": {
        "homeGoalsPerGame": 2.2,
        "awayGoalsPerGame": 1.4,
        "homeConcededPerGame": 1.2,
        "awayConcededPerGame": 2.2,
        "homeXGPerGame": 1.8,
        "awayXGPerGame": 1.2,
        "homePossessionPct": 55,
        "awayPossessionPct": 45,
        "homeShotsPerGame": 12.5,
        "awayShotsPerGame": 9.5,
        "homeCleanSheetPct": 50,
        "awayCleanSheetPct": 30
      },
      "players": {
        "keyPlayerHome": "Harry Kane — 10 goals, clinical finishing",
        "keyPlayerAway": "Moussa Niakhaté — 3 goals, defensive solidity",
        "injuriesHome": [
          "Ben Davies (ankle)"
        ],
        "injuriesAway": [
          "Orel Mangala (hamstring)"
        ]
      },
      "tactical analysis": {
        "homeFormation": "4-2-3-1",
        "awayFormation": "4-4-2",
        "tacticalMatchup": "Tottenham's high press will test Nottingham Forest's defense, while Nottingham Forest's midfield control could limit Tottenham's attacking opportunities.",
        "keyBattles": [
          "Harry Kane vs Cheikhou Kouyaté"
        ],
        "strengthsHome": [
          "Attacking prowess",
          "Midfield control"
        ],
        "strengthsAway": [
          "Defensive solidity"
        ],
        "weaknessesHome": [
          "Vulnerability on the counter"
        ],
        "weaknessesAway": [
          "Lack of pace in midfield"
        ]
      },
      "scoreline probabilities": [
        {
          "score": "2-0",
          "pct": 25
        },
        {
          "score": "1-0",
          "pct": 20
        },
        {
          "score": "3-0",
          "pct": 15
        }
      ],
      "match flow": {
        "halfTimePrediction": "1-0",
        "firstGoalTeam": "home",
        "matchTempoRating": 7,
        "dangerRating": 3
      },
      "additional markets": {
        "over15Pct": 85,
        "over35Pct": 30,
        "homeCleanSheetChance": 60,
        "awayCleanSheetChance": 20,
        "totalCornersEstimate": 9,
        "totalCardsEstimate": 3
      },
      "reasoning": [
        "Tottenham's home form has been solid this season.",
        "Nottingham Forest's away form has been poor.",
        "Tottenham's attacking prowess makes them strong favorites to win.",
        "Nottingham Forest's defense has struggled this season."
      ],
      "verdict": "Tottenham should win comfortably at home.",
      "matchDate": "2026-03-07T15:00:00Z"
    },
    {
      "homeTeam": "Aston Villa FC",
      "awayTeam": "Leeds United FC",
      "predictedScore": {
        "home": 1,
        "away": 1
      },
      "winner": "draw",
      "confidence": 50,
      "analysis": "Both sides have shown inconsistent form this season, and this match could be a draw.",
      "probabilities": {
        "homeWinPct": 30,
        "drawPct": 30,
        "awayWinPct": 40,
        "bttsYesPct": 70,
        "over25Pct": 50
      },
      "form & history": {
        "formHome": "LWDWD",
        "formAway": "DWWWW",
        "h2hSummary": "Home 2W-2D-2L in last 5 meetings",
        "homeLeaguePosition": 14,
        "awayLeaguePosition": 10
      },
      "team stats": {
        "homeGoalsPerGame": 1.8,
        "awayGoalsPerGame": 1.6,
        "homeConcededPerGame": 1.6,
        "awayConcededPerGame": 1.8,
        "homeXGPerGame": 1.4,
        "awayXGPerGame": 1.4,
        "homePossessionPct": 52,
        "awayPossessionPct": 48,
        "homeShotsPerGame": 11.5,
        "awayShotsPerGame": 10.5,
        "homeCleanSheetPct": 30,
        "awayCleanSheetPct": 40
      },
      "players": {
        "keyPlayerHome": "Ollie Watkins — 8 goals, clinical finishing",
        "keyPlayerAway": "Rasmus Kristensen — 3 goals, defensive solidity",
        "injuriesHome": [
          "Douglas Luiz (ankle)"
        ],
        "injuriesAway": [
          "Kalvin Phillips (knee)"
        ]
      },
      "tactical analysis": {
        "homeFormation": "4-2-3-1",
        "awayFormation": "4-2-3-1",
        "tacticalMatchup": "Both sides will look to control the midfield and create chances through set pieces.",
        "keyBattles": [
          "Ollie Watkins vs Rasmus Kristensen"
        ],
        "strengthsHome": [
          "Midfield control",
          "Set piece delivery"
        ],
        "strengthsAway": [
          "Defensive solidity",
          "Midfield control"
        ],
        "weaknessesHome": [
          "Vulnerability on the counter"
        ],
        "weaknessesAway": [
          "Lack of pace in midfield"
        ]
      },
      "scoreline probabilities": [
        {
          "score": "1-1",
          "pct": 25
        },
        {
          "score": "2-1",
          "pct": 15
        },
        {
          "score": "0-0",
          "pct": 10
        }
      ],
      "match flow": {
        "halfTimePrediction": "0-0",
        "firstGoalTeam": "either",
        "matchTempoRating": 6,
        "dangerRating": 2
      },
      "additional markets": {
        "over15Pct": 80,
        "over35Pct": 20,
        "homeCleanSheetChance": 20,
        "awayCleanSheetChance": 30,
        "totalCornersEstimate": 8.5,
        "totalCardsEstimate": 2.5
      },
      "reasoning": [
        "Aston Villa's home form has been inconsistent this season.",
        "Leeds United's away form has been inconsistent this season.",
        "Both sides have shown defensive solidity this season.",
        "This match could be a draw."
      ],
      "verdict": "A draw is likely at Villa Park.",
      "matchDate": "2026-03-07T15:00:00Z"
    },
    {
      "homeTeam": "Crystal Palace FC",
      "awayTeam": "Ipswich Town FC",
      "predictedScore": {
        "home": 2,
        "away": 0
      },
      "winner": "home",
      "confidence": 80,
      "analysis": "Crystal Palace's home form has been solid this season, and they should be able to beat a struggling Ipswich Town side.",
      "probabilities": {
        "homeWinPct": 80,
        "drawPct": 10,
        "awayWinPct": 10,
        "bttsYesPct": 40,
        "over25Pct": 60
      },
      "form & history": {
        "formHome": "WWWWD",
        "formAway": "LWWWW",
        "h2hSummary": "Home 3W-2D-0L in last 5 meetings",
        "homeLeaguePosition": 9,
        "awayLeaguePosition": 20
      },
      "team stats": {
        "homeGoalsPerGame": 2.2,
        "awayGoalsPerGame": 1.4,
        "homeConcededPerGame": 1.2,
        "awayConcededPerGame": 2.2,
        "homeXGPerGame": 1.8,
        "awayXGPerGame": 1.2,
        "homePossessionPct": 55,
        "awayPossessionPct": 45,
        "homeShotsPerGame": 12.5,
        "awayShotsPerGame": 9.5,
        "homeCleanSheetPct": 50,
        "awayCleanSheetPct": 30
      },
      "players": {
        "keyPlayerHome": "Wilfried Zaha — 8 goals, pace and skill",
        "keyPlayerAway": "Joe Bell — 3 goals, defensive solidity",
        "injuriesHome": [],
        "injuriesAway": [
          "Luke Matheson (ankle)"
        ]
      },
      "tactical analysis": {
        "homeFormation": "4-2-3-1",
        "awayFormation": "4-4-2",
        "tacticalMatchup": "Crystal Palace's high press will test Ipswich Town's defense, while Ipswich Town's midfield control could limit Crystal Palace's attacking opportunities.",
        "keyBattles": [
          "Wilfried Zaha vs Joe Bell"
        ],
        "strengthsHome": [
          "Attacking prowess",
          "Midfield control"
        ],
        "strengthsAway": [
          "Defensive solidity"
        ],
        "weaknessesHome": [
          "Vulnerability on the counter"
        ],
        "weaknessesAway": [
          "Lack of pace in midfield"
        ]
      },
      "scoreline probabilities": [
        {
          "score": "2-0",
          "pct": 25
        },
        {
          "score": "1-0",
          "pct": 20
        },
        {
          "score": "3-0",
          "pct": 15
        }
      ],
      "match flow": {
        "halfTimePrediction": "1-0",
        "firstGoalTeam": "home",
        "matchTempoRating": 7,
        "dangerRating": 3
      },
      "additional markets": {
        "over15Pct": 85,
        "over35Pct": 30,
        "homeCleanSheetChance": 60,
        "awayCleanSheetChance": 20,
        "totalCornersEstimate": 9,
        "totalCardsEstimate": 3
      },
      "reasoning": [
        "Crystal Palace's home form has been solid this season.",
        "Ipswich Town's away form has been poor.",
        "Crystal Palace's attacking prowess makes them strong favorites to win.",
        "Ipswich Town's defense has struggled this season."
      ],
      "verdict": "Crystal Palace should win comfortably at home.",
      "matchDate": "2026-03-07T15:00:00Z"
    },
    {
      "homeTeam": "Newcastle United FC",
      "awayTeam": "Fulham FC",
      "predictedScore": {
        "home": 1,
        "away": 1
      },
      "winner": "draw",
      "confidence": 50,
      "analysis": "Both sides have shown inconsistent form this season, and this match could be a draw.",
      "probabilities": {
        "homeWinPct": 30,
        "drawPct": 30,
        "awayWinPct": 40,
        "bttsYesPct": 70,
        "over25Pct": 50
      },
      "form & history": {
        "formHome": "LWWWD",
        "formAway": "DWWWW",
        "h2hSummary": "Home 2W-2D-2L in last 5 meetings",
        "homeLeaguePosition": 11,
        "awayLeaguePosition": 13
      },
      "team stats": {
        "homeGoalsPerGame": 1.8,
        "awayGoalsPerGame": 1.6,
        "homeConcededPerGame": 1.6,
        "awayConcededPerGame": 1.8,
        "homeXGPerGame": 1.4,
        "awayXGPerGame": 1.4,
        "homePossessionPct": 52,
        "awayPossessionPct": 48,
        "homeShotsPerGame": 11.5,
        "awayShotsPerGame": 10.5,
        "homeCleanSheetPct": 30,
        "awayCleanSheetPct": 40
      },
      "players": {
        "keyPlayerHome": "Callum Wilson — 8 goals, clinical finishing",
        "keyPlayerAway": "Willian — 5 goals, creativity and vision",
        "injuriesHome": [
          "Federico Fernández (ankle)"
        ],
        "injuriesAway": [
          "Antonee Robinson (hamstring)"
        ]
      },
      "tactical analysis": {
        "homeFormation": "4-2-3-1",
        "awayFormation": "4-2-3-1",
        "tacticalMatchup": "Both sides will look to control the midfield and create chances through set pieces.",
        "keyBattles": [
          "Callum Wilson vs Aleksandar Mitrović"
        ],
        "strengthsHome": [
          "Midfield control",
          "Set piece delivery"
        ],
        "strengthsAway": [
          "Defensive solidity",
          "Midfield control"
        ],
        "weaknessesHome": [
          "Vulnerability on the counter"
        ],
        "weaknessesAway": [
          "Lack of pace in midfield"
        ]
      },
      "scoreline probabilities": [
        {
          "score": "1-1",
          "pct": 25
        },
        {
          "score": "2-1",
          "pct": 15
        },
        {
          "score": "0-0",
          "pct": 10
        }
      ],
      "match flow": {
        "halfTimePrediction": "0-0",
        "firstGoalTeam": "either",
        "matchTempoRating": 6,
        "dangerRating": 2
      },
      "additional markets": {
        "over15Pct": 80,
        "over35Pct": 20,
        "homeCleanSheetChance": 20,
        "awayCleanSheetChance": 30,
        "totalCornersEstimate": 8.5,
        "totalCardsEstimate": 2.5
      },
      "reasoning": [
        "Newcastle United's home form has been inconsistent this season.",
        "Fulham's away form has been inconsistent this season.",
        "Both sides have shown defensive solidity this season.",
        "This match could be a draw."
      ],
      "verdict": "A draw is likely at St. James' Park.",
      "matchDate": "2026-03-07T15:00:00Z"
    },
    {
      "homeTeam": "Brentford FC",
      "awayTeam": "Everton FC",
      "predictedScore": {
        "home": 1,
        "away": 1
      },
      "winner": "draw",
      "confidence": 50,
      "analysis": "Both sides have shown inconsistent form this season, and this match could be a draw.",
      "probabilities": {
        "homeWinPct": 30,
        "drawPct": 30,
        "awayWinPct": 40,
        "bttsYesPct": 70,
        "over25Pct": 50
      },
      "form & history": {
        "formHome": "LWDWD",
        "formAway": "DWWWW",
        "h2hSummary": "Home 2W-2D-2L in last 5 meetings",
        "homeLeaguePosition": 12,
        "awayLeaguePosition": 16
      },
      "team stats": {
        "homeGoalsPerGame": 1.8,
        "awayGoalsPerGame": 1.6,
        "homeConcededPerGame": 1.6,
        "awayConcededPerGame": 1.8,
        "homeXGPerGame": 1.4,
        "awayXGPerGame": 1.4,
        "homePossessionPct": 52,
        "awayPossessionPct": 48,
        "homeShotsPerGame": 11.5,
        "awayShotsPerGame": 10.5,
        "homeCleanSheetPct": 30,
        "awayCleanSheetPct": 40
      },
      "players": {
        "keyPlayerHome": "Christian Nørgaard — 5 goals, midfield control",
        "keyPlayerAway": "Dominic Calvert-Lewin — 8 goals, pace and skill",
        "injuriesHome": [
          "Ethan Pinnock (ankle)"
        ],
        "injuriesAway": [
          "André Gomes (hamstring)"
        ]
      },
      "tactical analysis": {
        "homeFormation": "4-2-3-1",
        "awayFormation": "4-2-3-1",
        "tacticalMatchup": "Both sides will look to control the midfield and create chances through set pieces.",
        "keyBattles": [
          "Christian Nørgaard vs Dominic Calvert-Lewin"
        ],
        "strengthsHome": [
          "Midfield control",
          "Set piece delivery"
        ],
        "strengthsAway": [
          "Defensive solidity",
          "Midfield control"
        ],
        "weaknessesHome": [
          "Vulnerability on the counter"
        ],
        "weaknessesAway": [
          "Lack of pace in midfield"
        ]
      },
      "scoreline probabilities": [
        {
          "score": "1-1",
          "pct": 25
        },
        {
          "score": "2-1",
          "pct": 15
        },
        {
          "score": "0-0",
          "pct": 10
        }
      ],
      "match flow": {
        "halfTimePrediction": "0-0",
        "firstGoalTeam": "either",
        "matchTempoRating": 6,
        "dangerRating": 2
      },
      "additional markets": {
        "over15Pct": 80,
        "over35Pct": 20,
        "homeCleanSheetChance": 20,
        "awayCleanSheetChance": 30,
        "totalCornersEstimate": 8.5,
        "totalCardsEstimate": 2.5
      },
      "reasoning": [
        "Brentford's home form has been inconsistent this season.",
        "Everton's away form has been inconsistent this season.",
        "Both sides have shown defensive solidity this season.",
        "This match could be a draw."
      ],
      "verdict": "A draw is likely at Brentford Community Stadium.",
      "matchDate": "2026-03-07T15:00:00Z"
    },
    {
      "homeTeam": "Southampton FC",
      "awayTeam": "Brighton & Hove Albion FC",
      "predictedScore": {
        "home": 0,
        "away": 1
      },
      "winner": "away",
      "confidence": 60,
      "analysis": "Brighton's away form has been solid this season, and they should be able to beat a struggling Southampton side.",
      "probabilities": {
        "homeWinPct": 20,
        "drawPct": 20,
        "awayWinPct": 60,
        "bttsYesPct": 50,
        "over25Pct": 40
      },
      "form & history": {
        "formHome": "LLDLL",
        "formAway": "WWWDW",
        "h2hSummary": "Home 2W-3D-1L in last 5 meetings",
        "homeLeaguePosition": 17,
        "awayLeaguePosition": 8
      },
      "team stats": {
        "homeGoalsPerGame": 1.2,
        "awayGoalsPerGame": 1.4,
        "homeConcededPerGame": 2.2,
        "awayConcededPerGame": 1.2,
        "homeXGPerGame": 1,
        "awayXGPerGame": 1.4,
        "homePossessionPct": 45,
        "awayPossessionPct": 55,
        "homeShotsPerGame": 9.5,
        "awayShotsPerGame": 11.5,
        "homeCleanSheetPct": 20,
        "awayCleanSheetPct": 50
      },
      "players": {
        "keyPlayerHome": "Che Adams — 5 goals, clinical finishing",
        "keyPlayerAway": "Adam Lallana — 5 goals, creativity and vision",
        "injuriesHome": [
          "Armando Broja (ankle)"
        ],
        "injuriesAway": []
      },
      "tactical analysis": {
        "homeFormation": "4-4-2",
        "awayFormation": "4-2-3-1",
        "tacticalMatchup": "Brighton's high press will test Southampton's defense, while Southampton's midfield control could limit Brighton's attacking opportunities.",
        "keyBattles": [
          "Che Adams vs Adam Lallana"
        ],
        "strengthsHome": [
          "Midfield control"
        ],
        "strengthsAway": [
          "Defensive solidity",
          "Midfield control"
        ],
        "weaknessesHome": [
          "Vulnerability on the counter"
        ],
        "weaknessesAway": [
          "Lack of pace in midfield"
        ]
      },
      "scoreline probabilities": [
        {
          "score": "0-1",
          "pct": 30
        },
        {
          "score": "1-0",
          "pct": 20
        },
        {
          "score": "0-0",
          "pct": 10
        }
      ],
      "match flow": {
        "halfTimePrediction": "0-0",
        "firstGoalTeam": "away",
        "matchTempoRating": 7,
        "dangerRating": 3
      },
      "additional markets": {
        "over15Pct": 70,
        "over35Pct": 20,
        "homeCleanSheetChance": 10,
        "awayCleanSheetChance": 60,
        "totalCornersEstimate": 8,
        "totalCardsEstimate": 3
      },
      "reasoning": [
        "Brighton's away form has been solid this season.",
        "Southampton's home form has been poor.",
        "Brighton's defensive solidity makes them strong favorites to win.",
        "Southampton's attack has struggled this season."
      ],
      "verdict": "Brighton should win comfortably at Southampton.",
      "matchDate": "2026-03-07T15:00:00Z"
    },
    {
      "homeTeam": "Arsenal FC",
      "awayTeam": "Manchester United FC",
      "predictedScore": {
        "home": 2,
        "away": 1
      },
      "winner": "home",
      "confidence": 70,
      "analysis": "Arsenal's home form has been solid this season, and they should be able to beat a struggling Manchester United side.",
      "probabilities": {
        "homeWinPct": 70,
        "drawPct": 15,
        "awayWinPct": 15,
        "bttsYesPct": 60,
        "over25Pct": 70
      },
      "form & history": {
        "formHome": "WWWWW",
        "formAway": "LDWWW",
        "h2hSummary": "Home 4W-2D-1L in last 5 meetings",
        "homeLeaguePosition": 2,
        "awayLeaguePosition": 4
      },
      "team stats": {
        "homeGoalsPerGame": 2.2,
        "awayGoalsPerGame": 1.8,
        "homeConcededPerGame": 1.2,
        "awayConcededPerGame": 1.8,
        "homeXGPerGame": 1.8,
        "awayXGPerGame": 1.4,
        "homePossessionPct": 55,
        "awayPossessionPct": 45,
        "homeShotsPerGame": 12.5,
        "awayShotsPerGame": 10.5,
        "homeCleanSheetPct": 50,
        "awayCleanSheetPct": 40
      },
      "players": {
        "keyPlayerHome": "Bukayo Saka — 8 goals, pace and skill",
        "keyPlayerAway": "Marcus Rashford — 10 goals, clinical finishing",
        "injuriesHome": [],
        "injuriesAway": [
          "Harry Maguire (ankle)"
        ]
      },
      "tactical analysis": {
        "homeFormation": "4-2-3-1",
        "awayFormation": "4-2-3-1",
        "tacticalMatchup": "Arsenal's high press will test Manchester United's defense, while Manchester United's midfield control could limit Arsenal's attacking opportunities.",
        "keyBattles": [
          "Bukayo Saka vs Marcus Rashford"
        ],
        "strengthsHome": [
          "Attacking prowess",
          "Midfield control"
        ],
        "strengthsAway": [
          "Defensive solidity",
          "Midfield control"
        ],
        "weaknessesHome": [
          "Vulnerability on the counter"
        ],
        "weaknessesAway": [
          "Lack of pace in midfield"
        ]
      },
      "scoreline probabilities": [
        {
          "score": "2-1",
          "pct": 25
        },
        {
          "score": "3-1",
          "pct": 15
        },
        {
          "score": "1-0",
          "pct": 10
        }
      ],
      "match flow": {
        "halfTimePrediction": "1-0",
        "firstGoalTeam": "home",
        "matchTempoRating": 8,
        "dangerRating": 4
      },
      "additional markets": {
        "over15Pct": 85,
        "over35Pct": 35,
        "homeCleanSheetChance": 60,
        "awayCleanSheetChance": 20,
        "totalCornersEstimate": 9.5,
        "totalCardsEstimate": 3.5
      },
      "reasoning": [
        "Arsenal's home form has been solid this season.",
        "Manchester United's away form has been poor.",
        "Arsenal's attacking prowess makes them strong favorites to win.",
        "Manchester United's defense has struggled this season."
      ],
      "verdict": "Arsenal should win comfortably at home.",
      "matchDate": "2026-03-09T20:00:00Z"
    },
    {
      "homeTeam": "Leicester City FC",
      "awayTeam": "AFC Bournemouth FC",
      "predictedScore": {
        "home": 2,
        "away": 0
      },
      "winner": "home",
      "confidence": 80,
      "analysis": "Leicester's home form has been solid this season, and they should be able to beat a struggling Bournemouth side.",
      "probabilities": {
        "homeWinPct": 80,
        "drawPct": 10,
        "awayWinPct": 10,
        "bttsYesPct": 40,
        "over25Pct": 60
      },
      "form & history": {
        "formHome": "WWWWD",
        "formAway": "DWLWW",
        "h2hSummary": "Home 4W-1D-0L in last 5 meetings",
        "homeLeaguePosition": 3,
        "awayLeaguePosition": 19
      },
      "team stats": {
        "homeGoalsPerGame": 2.2,
        "awayGoalsPerGame": 1.4,
        "homeConcededPerGame": 1.2,
        "awayConcededPerGame": 2.2,
        "homeXGPerGame": 1.8,
        "awayXGPerGame": 1.2,
        "homePossessionPct": 55,
        "awayPossessionPct": 45,
        "homeShotsPerGame": 12.5,
        "awayShotsPerGame": 9.5,
        "homeCleanSheetPct": 50,
        "awayCleanSheetPct": 30
      },
      "players": {
        "keyPlayerHome": "Jamie Vardy — 10 goals, clinical finishing",
        "keyPlayerAway": "Dominic Solanke — 5 goals, pace and skill",
        "injuriesHome": [],
        "injuriesAway": [
          "Philip Billing (ankle)"
        ]
      },
      "tactical analysis": {
        "homeFormation": "4-2-3-1",
        "awayFormation": "4-4-2",
        "tacticalMatchup": "Leicester's high press will test Bournemouth's defense, while Bournemouth's midfield control could limit Leicester's attacking opportunities.",
        "keyBattles": [
          "Jamie Vardy vs Dominic Solanke"
        ],
        "strengthsHome": [
          "Attacking prowess",
          "Midfield control"
        ],
        "strengthsAway": [
          "Defensive solidity"
        ],
        "weaknessesHome": [
          "Vulnerability on the counter"
        ],
        "weaknessesAway": [
          "Lack of pace in midfield"
        ]
      },
      "scoreline probabilities": [
        {
          "score": "2-0",
          "pct": 25
        },
        {
          "score": "1-0",
          "pct": 20
        },
        {
          "score": "3-0",
          "pct": 15
        }
      ],
      "match flow": {
        "halfTimePrediction": "1-0",
        "firstGoalTeam": "home",
        "matchTempoRating": 7,
        "dangerRating": 3
      },
      "additional markets": {
        "over15Pct": 85,
        "over35Pct": 30,
        "homeCleanSheetChance": 60,
        "awayCleanSheetChance": 20,
        "totalCornersEstimate": 9,
        "totalCardsEstimate": 3
      },
      "reasoning": [
        "Leicester's home form has been solid this season.",
        "Bournemouth's away form has been poor.",
        "Leicester's attacking prowess makes them strong favorites to win.",
        "Bournemouth's defense has struggled this season."
      ],
      "verdict": "Leicester should win comfortably at home.",
      "matchDate": "2026-03-10T19:30:00Z"
    }
  ]
}